notifier/__init__.py
notifier/__main__.py
notifier/break.ico
notifier/end.ico
notifier/food.ico
notifier/main.py
notifier/sea_fishes.ico
notipy_py-1.0.8.dist-info/METADATA
notipy_py-1.0.8.dist-info/WHEEL
notipy_py-1.0.8.dist-info/entry_points.txt
notipy_py-1.0.8.dist-info/top_level.txt
notipy_py-1.0.8.dist-info/RECORD
